openmacro/__init__.py
openmacro/__main__.py
openmacro/config.default.toml
openmacro/core/cli.py
openmacro/core/core.py
openmacro/core/prompts/initial.txt
openmacro/core/prompts/instructions.txt
openmacro/core/prompts/interface.txt
openmacro/core/utils/computer.py
openmacro/core/utils/extensions.py
openmacro/core/utils/general.py
openmacro/core/utils/llm.py
openmacro/extensions/browser/__init__.py
openmacro/extensions/browser/browser.py
openmacro/extensions/browser/config.default.toml
openmacro/extensions/browser/docs/docs.md
openmacro/extensions/browser/docs/instructions.md
openmacro/extensions/browser/omproject.toml
openmacro/extensions/browser/src/engines.json
openmacro/extensions/browser/src/user_agents.txt
openmacro/extensions/browser/tests/tests.py
openmacro/extensions/browser/utils/general.py
openmacro/extensions/browser/utils/google.py
openmacro/tests/__init__.py
openmacro/tests/cases/browser.py
openmacro-0.1.9.dist-info/entry_points.txt
openmacro-0.1.9.dist-info/LICENSE
openmacro-0.1.9.dist-info/METADATA
openmacro-0.1.9.dist-info/WHEEL
openmacro-0.1.9.dist-info/RECORD
