Metadata-Version: 2.1
Name: openmacro
Version: 0.1.9
Summary: Multimodal Assistant. Human Interface for computers.
Home-page: https://github.com/amooo-ooo/openmacro
License: MIT
Author: Amor Budiyanto
Author-email: amor.budiyanto@gmail.com
Requires-Python: >=3.8,<4.0
Classifier: License :: OSI Approved :: MIT License
Classifier: Programming Language :: Python :: 3
Classifier: Programming Language :: Python :: 3.8
Classifier: Programming Language :: Python :: 3.9
Classifier: Programming Language :: Python :: 3.10
Classifier: Programming Language :: Python :: 3.11
Classifier: Programming Language :: Python :: 3.12
Provides-Extra: dev
Requires-Dist: asyncio
Requires-Dist: beautifulsoup4
Requires-Dist: chromadb
Requires-Dist: gradio_client (>=1.3.0)
Requires-Dist: markdownify
Requires-Dist: playwright
Requires-Dist: pybrowsers
Requires-Dist: rich (>=10.0)
Requires-Dist: snova (>=0.1.3)
Requires-Dist: toml (>=0.10)
